<?xml version="1.0" encoding="UTF-8"?>
<akn:akomaNtoso xmlns:akn="http://docs.oasis-open.org/legaldocml/ns/akn/3.0"><akn:act name="statute"><akn:meta><akn:identification source="#legislature-ne"><akn:FRBRWork><akn:FRBRthis value="/akn/us-ne/act/80/404.02" /><akn:FRBRuri value="/akn/us-ne/act/80/404.02" /><akn:FRBRdate date="2025-12-31" name="generation" /><akn:FRBRauthor href="#legislature-ne" /><akn:FRBRcountry value="us-ne" /><akn:FRBRnumber value="80-404.02" /></akn:FRBRWork><akn:FRBRExpression><akn:FRBRthis value="/akn/us-ne/act/80/404.02/eng@2025-12-31" /><akn:FRBRuri value="/akn/us-ne/act/80/404.02/eng@2025-12-31" /><akn:FRBRdate date="2025-12-31" name="generation" /><akn:FRBRauthor href="#cosilico" /><akn:FRBRlanguage language="eng" /></akn:FRBRExpression><akn:FRBRManifestation><akn:FRBRthis value="/akn/us-ne/act/80/404.02/eng@2025-12-31/akn.xml" /><akn:FRBRuri value="/akn/us-ne/act/80/404.02/eng@2025-12-31/akn.xml" /><akn:FRBRdate date="2025-12-31" name="generation" /><akn:FRBRauthor href="#cosilico" /></akn:FRBRManifestation></akn:identification><akn:publication date="2025-12-31" name="Nebraska Revised Statutes" showAs="Nebraska Revised Statutes" /></akn:meta><akn:body><akn:chapter eId="chp_80"><akn:num>80</akn:num><akn:section eId="sec_80-404_02"><akn:num>80-404.02</akn:num><akn:heading>Repealed. Laws 1953, c. 326, ยง 5.</akn:heading><akn:content /></akn:section></akn:chapter></akn:body></akn:act></akn:akomaNtoso>